{
    "projects": [
        {
            "title": "Personal Portfolio",
            "src": "../img/portfolio-400.png",
            "alt": "The front page of Alexander's personal portfolio website.",
            "description": "This website showcases my work using semantic HTML and accessible design.",
            "link": "https://github.com/Areco892/cse134B-hw5"
        },
        {
            "title": "Math Game",
            "src": "../img/math_game-400.png",
            "alt": "The game screen of a math game website that quizzes students on highschool math topics, like linear equations.",
            "description": "An educational website game that quizzes students on highschool math topics, like linear equations.",
            "link": "https://github.com/Areco892/cse-110-project-38"
        },
        {
            "title": "Interactive Lemon",
            "src": "../img/interactive_lemon-400.png",
            "alt": "An image of a whole lemon drawn in a computer.",
            "description": "An interactive website that has a lemon which can be clicked on and also be moved around.",
            "link": "https://github.com/Areco892/110-lab1"
        },
        {
            "title": "Lemon Clicker",
            "src": "",
            "alt": "The game screen of a lemon clicking game.",
            "description": "A clicking game where the objective is to click on the lemons shown on the screen as fast as you can.",
            "link": "https://github.com/Areco892/110-lab3"
        }
    ]
}